git_miner/__init__.py
git_miner/__main__.py
git_miner/cli.py
git_miner/config.py
git_miner/constants.py
git_miner/state_db.py
git_miner/token_cache.py
git_miner/api/__init__.py
git_miner/api/client.py
git_miner/api/exceptions.py
git_miner/api/models.py
git_miner/datasets/__init__.py
git_miner/datasets/builder.py
git_miner/datasets/export.py
git_miner/datasets/schemas.py
git_miner/extractors/__init__.py
git_miner/extractors/activity.py
git_miner/extractors/base.py
git_miner/extractors/contributors.py
git_miner/extractors/repository.py
git_miner/search/__init__.py
git_miner/search/engine.py
git_miner/search/query.py
git_miner/utils/__init__.py
git_miner/utils/progress.py
git_miner-0.2.6.dist-info/METADATA
git_miner-0.2.6.dist-info/WHEEL
git_miner-0.2.6.dist-info/entry_points.txt
git_miner-0.2.6.dist-info/licenses/LICENSE
git_miner-0.2.6.dist-info/RECORD
