Metadata-Version: 2.4
Name: git-miner
Version: 0.2.6
Summary: A tool for mining GitHub repository metadata and activity data
Project-URL: Homepage, https://github.com/dev-dami/GITMiner
Project-URL: Documentation, https://github.com/dev-dami/GITMiner#readme
Project-URL: Repository, https://github.com/dev-dami/GITMiner
Project-URL: Issues, https://github.com/dev-dami/GITMiner/issues
Author: Git Miner Contributors
License: Apache-2.0
License-File: LICENSE
Keywords: api,data-science,dataset,github,mining
Classifier: Development Status :: 3 - Alpha
Classifier: Intended Audience :: Developers
Classifier: Intended Audience :: Science/Research
Classifier: License :: OSI Approved :: Apache Software License
Classifier: Programming Language :: Python :: 3
Classifier: Programming Language :: Python :: 3.11
Classifier: Programming Language :: Python :: 3.12
Classifier: Programming Language :: Python :: 3.13
Classifier: Topic :: Scientific/Engineering :: Information Analysis
Classifier: Topic :: Software Development :: Libraries
Requires-Python: >=3.11
Requires-Dist: httpx>=0.27.0
Requires-Dist: pandas>=2.0.0
Requires-Dist: pyarrow>=14.0.0
Requires-Dist: pydantic>=2.0.0
Requires-Dist: toml>=0.10.2
Requires-Dist: tqdm>=4.66.0
Requires-Dist: typer>=0.12.0
Provides-Extra: dev
Requires-Dist: mypy>=1.10.0; extra == 'dev'
Requires-Dist: pytest-asyncio>=0.23.0; extra == 'dev'
Requires-Dist: pytest-cov>=5.0.0; extra == 'dev'
Requires-Dist: pytest>=8.0.0; extra == 'dev'
Requires-Dist: respx>=0.21.0; extra == 'dev'
Requires-Dist: ruff>=0.5.0; extra == 'dev'
